{"assets":{"9FD575C40A5DBF36AF0AF50BDD3DD8B4":{"type":"texture","index":0,"assetRequest":{"type":"slide","state":"contents","slide":"none"},"url":{"native":"assets/B53B0AE5-FAAB-4E1A-9063-52C9980F02B1.pdf"},"width":1024,"height":768},"33A8F49F191CCA91E73BD2DF4F8EDB19":{"type":"texture","index":1,"assetRequest":{"type":"slide","state":"contents","slide":"none"},"url":{"native":"assets/B53B0AE5-FAAB-4E1A-9063-52C9980F02B1.pdf"},"width":1024,"height":768}},"events":[{"effects":[{"beginTime":0,"baseLayer":{"animations":[],"initialState":{"affineTransform":[1,0,0,1,0,0],"masksToBounds":false,"rotation":0,"scale":1,"position":{"pointX":512,"pointY":384},"width":1024,"sublayerTransform":[1,0,0,0,0,1,0,0,0,0,1,0,0,0,0,1],"contentsRect":{"y":0,"x":0,"width":1,"height":1},"opacity":1,"edgeAntialiasingMask":251658240,"height":768,"hidden":false,"anchorPoint":{"pointX":0.5,"pointY":0.5}},"objectID":"0","layers":[{"animations":[],"initialState":{"affineTransform":[1,0,0,1,0,0],"masksToBounds":false,"rotation":0,"scale":1,"position":{"pointX":512,"pointY":384},"width":1024,"sublayerTransform":[1,0,0,0,0,1,0,0,0,0,1,-0.0004922987690640373,0,0,0,1],"contentsRect":{"y":0,"x":0,"width":1,"height":1},"opacity":1,"edgeAntialiasingMask":251658240,"height":768,"hidden":false,"anchorPoint":{"pointX":0.5,"pointY":0.5}},"layers":[{"animations":[],"layers":[],"texturedRectangle":{"isBackgroundTexture":false,"singleTextureOpacity":1,"textureType":0,"textBaseline":0,"textXHeight":0,"isVerticalText":false},"initialState":{"affineTransform":[1,0,0,1,0,0],"masksToBounds":false,"rotation":0,"scale":1,"position":{"pointX":512,"pointY":384},"width":1024,"sublayerTransform":[1,0,0,0,0,1,0,0,0,0,1,0,0,0,0,1],"contentsRect":{"y":0,"x":0,"width":1,"height":1},"opacity":1,"edgeAntialiasingMask":0,"height":768,"hidden":false,"anchorPoint":{"pointX":0.5,"pointY":0.5}},"texture":"33A8F49F191CCA91E73BD2DF4F8EDB19"},{"animations":[{"timeOffset":0,"from":{"scalar":false},"beginTime":0,"repeatCount":0,"fillMode":"both","property":"hidden","autoreverses":false,"duration":0.01,"to":{"scalar":true}}],"layers":[],"texturedRectangle":{"isBackgroundTexture":false,"singleTextureOpacity":1,"textureType":0,"textBaseline":0,"textXHeight":0,"isVerticalText":false},"initialState":{"affineTransform":[1,0,0,1,0,0],"masksToBounds":false,"rotation":0,"scale":1,"position":{"pointX":512,"pointY":384},"width":1024,"sublayerTransform":[1,0,0,0,0,1,0,0,0,0,1,0,0,0,0,1],"contentsRect":{"y":0,"x":0,"width":1,"height":1},"opacity":1,"edgeAntialiasingMask":0,"height":768,"hidden":false,"anchorPoint":{"pointX":0.5,"pointY":0.5}},"texture":"9FD575C40A5DBF36AF0AF50BDD3DD8B4"}]}]},"effects":[],"duration":0.01,"type":"transition","name":"none","objectID":"0"}],"automaticPlay":false,"hyperlinks":[],"accessibility":[{"text":"2주의 짧은 기간에 DengDengE 웹페이지 제작과 DengAdmin 페이지 제작을 진행함에 있어서 완성도 있는 개발을 하는 것에 가장 큰 목표를 두었다.","targetRectangle":{"y":208.4999999900502,"x":103.0625000397051,"width":840.9939999999999,"height":57.01408314704898}},{"text":"javascript, jQuery, ajax를 사용하는데 큰 어려움이 없을 정도로 자신감을 붙였고, ajax의 동작 원리를 이해하고 자유롭게 사용할 수 있었다.","targetRectangle":{"y":266.1522362132711,"x":103.0625000397051,"width":841.9375000000002,"height":83.4140830039978}},{"text":"외부 API ( Gson, Daum Map, DataTable ... ) 를 사용하는 것이 많이 익숙해졌고, API Document를 읽고 분석하여 사용하는 것이 능숙해졌다.","targetRectangle":{"y":350.2044722934407,"x":103.0625000397051,"width":786.0159999999996,"height":83.4140830039978}},{"text":"부트스트랩을 사용하여 기본틀이 잡힌 웹페이지를 큰 어려움 없이 제작할 수 있을 것 같다.","targetRectangle":{"y":434.2567083736104,"x":103.0625000397051,"width":764.5879999999991,"height":54.58796489238739}},{"text":"Model2 의 구조를 더 확고히 이해할 수 있었다. ","targetRectangle":{"y":489.4828263421697,"x":103.0625000397051,"width":417.8679999999998,"height":54.58796489238739}},{"text":"이전 회사에서 관리자 페이지의 유지보수를 했던 경험이 이번 프로젝트를 진행하는데 큰 도움이 되었고, 앞으로 관리자 페이지에 대한 기능 구현에 대한 프로세스를 이해할 수 있었다.데이터 베이스 쿼리의 사용을 더 활용하지 못한 점이 아쉽다. 앞으로 사용자의 사용을 분석하는 곳에 데이터 베이스 쿼리를 적극 활용하여 효율적인 데이터 추출을 할 수 있도록 보안하고 개발해야겠다.","targetRectangle":{"y":544.708944310729,"x":103.0625000397051,"width":834.5919999999996,"height":141.0663192272186}},{"text":"Deng Admin 개발 후기","targetRectangle":{"y":54,"x":123.92,"width":776.1600000000001,"height":101.3198728561401}}],"baseLayer":{"animations":[],"initialState":{"affineTransform":[1,0,0,1,0,0],"masksToBounds":false,"rotation":0,"scale":1,"position":{"pointX":512,"pointY":384},"width":1024,"sublayerTransform":[1,0,0,0,0,1,0,0,0,0,1,0,0,0,0,1],"contentsRect":{"y":0,"x":0,"width":1,"height":1},"opacity":1,"edgeAntialiasingMask":251658240,"height":768,"hidden":false,"anchorPoint":{"pointX":0.5,"pointY":0.5}},"objectID":"0","layers":[{"animations":[],"initialState":{"affineTransform":[1,0,0,1,0,0],"masksToBounds":false,"rotation":0,"scale":1,"position":{"pointX":512,"pointY":384},"width":1024,"sublayerTransform":[1,0,0,0,0,1,0,0,0,0,1,-0.0004922987690640373,0,0,0,1],"contentsRect":{"y":0,"x":0,"width":1,"height":1},"opacity":1,"edgeAntialiasingMask":251658240,"height":768,"hidden":false,"anchorPoint":{"pointX":0.5,"pointY":0.5}},"layers":[{"animations":[],"layers":[],"texturedRectangle":{"isBackgroundTexture":false,"singleTextureOpacity":1,"textureType":0,"textBaseline":0,"textXHeight":0,"isVerticalText":false},"initialState":{"affineTransform":[1,0,0,1,0,0],"masksToBounds":false,"rotation":0,"scale":1,"position":{"pointX":512,"pointY":384},"width":1024,"sublayerTransform":[1,0,0,0,0,1,0,0,0,0,1,0,0,0,0,1],"contentsRect":{"y":0,"x":0,"width":1,"height":1},"opacity":1,"edgeAntialiasingMask":0,"height":768,"hidden":false,"anchorPoint":{"pointX":0.5,"pointY":0.5}},"texture":"9FD575C40A5DBF36AF0AF50BDD3DD8B4"}]}]}}]}